rsolve/__init__.py
rsolve/atom_formula.py
rsolve/build_dnf.py
rsolve/interface.py
rsolve/normal.py
rsolve/well_defined_forms.py
rsolve/hm/__init__.py
rsolve/hm/hm.py
rsolve/hm/nominal.py
rsolve/hm/unification.py
test/__init__.py
test/test_hm.py
test/test_wff.py
rsolve.py-0.1.dist-info/LICENSE
rsolve.py-0.1.dist-info/METADATA
rsolve.py-0.1.dist-info/WHEEL
rsolve.py-0.1.dist-info/top_level.txt
rsolve.py-0.1.dist-info/RECORD
