Metadata-Version: 2.1
Name: rsolve.py
Version: 0.1
Summary: For constraint satisfaction problems in Python
Home-page: https://github.com/thautwarm/rsolve.py
Author: thautwarm
Author-email: twshere@outlook.com
License: MIT
Platform: UNKNOWN
Classifier: Programming Language :: Python :: 3.6
Classifier: Programming Language :: Python :: 3.7
Classifier: Programming Language :: Python :: Implementation :: CPython
Requires-Python: >=3.6.0
